CHANGES.txt
LICENSE
MANIFEST.in
README.rst
py26-requirements.txt
requirements.txt
setup.py
crosswords/__init__.py
crosswords/cli.py
crosswords/dictionnaries.py
crosswords/words.py
crosswords.egg-info/PKG-INFO
crosswords.egg-info/SOURCES.txt
crosswords.egg-info/dependency_links.txt
crosswords.egg-info/entry_points.txt
crosswords.egg-info/requires.txt
crosswords.egg-info/top_level.txt