Metadata-Version: 1.1
Name: crosswords
Version: 0.3.2
Summary: Crosswords help in your terminal
Home-page: https://github.com/bfontaine/crosswords
Author: Baptiste Fontaine
Author-email: b@ptistefontaine.fr
License: Copyright © 2014-2015 – Baptiste Fontaine
